{
    "id": "c0200a6c-1b8a-4365-9f1b-32d753194335",
    "serialNumber": "CK012345ARB",
    "productDescription": "Aruba AP-215 Dual 3x3:3 802.11ac AP",
    "assetType": "Software",
    "vendor": "HPE",
    "sku": "JW1123",
    "eolDate": "1615161600000",
    "eosDate": "",
    "country": "Great Britain",
    "latitude": "51.5",
    "longitude": "-0.116667",
    "countryCode": "GB",
    "zip": "70618",
    "city": "Port Adanville",
    "address": "Maddison Path Suite 820 Apt. 898",
    "address2": "",
    "resellerId": "97292d03-7919-406c-a15b-39bf029e6d5a",
    "customerId": "5fb52fc3-86fd-4e1f-87cd-0f546fc8989a",
    "assetDocument": [
        {
            "document": {
                "id": "688b9621-3244-464b-9468-3cd74f5eaacf",
                "type": "MultiNational Quote",
                "startDate": null,
                "endDate": "1614470400000",
                "currencyCode": "CUR",
                "languageCode": "fr",
                "totalNetPrice": "1,292.16",
                "vendorSpecificFields": {
                    "vendor": "HPE",
                    "said": "1234 4678 9012",
                    "groupId": "abc-de",
                    "groupDescription": "description"
                },
                "documentNumber": "0056523287",
                "contactPersons": [
                    {
                        "phoneNumber": "+49 (591) 12345-67",
                        "vendor": "HPE",
                        "name": "Alice Marks",
                        "type": "HARDWARE_CONTACT",
                        "mail": "alice1@hpe.com"
                    }
                ],
                "resellerId": "97292d03-7919-406c-a15b-39bf029e6d5a",
                "customerId": "5fb52fc3-86fd-4e1f-87cd-0f546fc8989a",
                "distributorId": "2d4c0f62-7e8f-4001-b16a-131db759c3f4"
            },
            "skuNumber": "HA151AC",
            "skuDescription": "HPE Hardware Maintenance Onsite Support",
            "supportPackage": "H7J34AC",
            "supportPackageDescription": "HPE Foundation Care 24x7 SVC",
            "startDate": null,
            "endDate": "1614470400000",
            "warrantyEndDate": null,
            "netPrice": "23.4",
            "discount": "-2.05",
            "listPrice": "48",
            "currencyCode": "EUR",
            "estimatedValueRenewal": "145"
        },
        {
            "document": {
                "id": "7e6b6976-cb1b-4b2a-9cf1-de9e768e8802",
                "type": "MultiNational Quote",
                "startDate": null,
                "endDate": "1677542400000",
                "currencyCode": "CUR",
                "languageCode": "en",
                "totalNetPrice": "3,646.44",
                "vendorSpecificFields": {
                    "vendor": "HPE2"
                },
                "documentNumber": "0056523288",
                "contactPersons": [
                    {
                        "phoneNumber": "+49 (591) 12345-68",
                        "vendor": "HPE2",
                        "name": "Alice Marks2",
                        "type": "HARDWARE_CONTACT",
                        "mail": "alice2@hpe.com"
                    }
                ],
                "resellerId": "97292d03-7919-406c-a15b-39bf029e6d5a",
                "customerId": "5fb52fc3-86fd-4e1f-87cd-0f546fc8989a",
                "distributorId": "2d4c0f62-7e8f-4001-b16a-131db759c3f4"
            },
            "skuNumber": "HL935AC",
            "skuDescription": "HPE Collaborative Remote Support",
            "supportPackage": "H7J34AC",
            "supportPackageDescription": "HPE Foundation Care 24x7 SVC",
            "startDate": null,
            "endDate": "1677542400000",
            "warrantyEndDate": null,
            "netPrice": "23.4",
            "discount": "-2.05",
            "listPrice": "48",
            "currencyCode": "EUR",
            "estimatedValueRenewal": "25"
        },
        {
            "document": {
                "id": "dbd3f08b-6bd1-4e28-8122-3004257879c0",
                "type": "MultiNational Quote",
                "startDate": null,
                "endDate": "1740700800000",
                "currencyCode": "CUR",
                "languageCode": "fr",
                "totalNetPrice": "6,376.15",
                "vendorSpecificFields": {
                    "vendor": "HPE"
                },
                "documentNumber": "0056490551",
                "contactPersons": [
                    {
                        "phoneNumber": "+49 (591) 12345-68",
                        "vendor": "HPE",
                        "name": "Alice Marks3",
                        "type": "HARDWARE_CONTACT",
                        "mail": "alice3@hpe.com"
                    }
                ],
                "resellerId": "97292d03-7919-406c-a15b-39bf029e6d5a",
                "customerId": "5fb52fc3-86fd-4e1f-87cd-0f546fc8989a",
                "distributorId": "2d4c0f62-7e8f-4001-b16a-131db759c3f4"
            },
            "skuNumber": "HL935AC",
            "skuDescription": "HPE Collaborative Remote Support",
            "supportPackage": "H7J34AC",
            "supportPackageDescription": "HPE Foundation Care 24x7 SVC",
            "startDate": null,
            "endDate": "1740700800000",
            "warrantyEndDate": null,
            "netPrice": "23.4",
            "discount": "-2.05",
            "listPrice": "48",
            "currencyCode": "EUR",
            "estimatedValueRenewal": "10.44"
        },
        {
            "document": {
                "id": "688b9621-3244-464b-9468-3cd74f5eaacf",
                "type": "MultiNational Quote",
                "startDate": null,
                "endDate": "1614470400000",
                "currencyCode": "CUR",
                "languageCode": "fr",
                "totalNetPrice": "1,292.16",
                "vendorSpecificFields": {
                    "vendor": "HPE",
                    "said": "1234 4678 9012",
                    "groupId": "abc-de",
                    "groupDescription": "description"
                },
                "documentNumber": "0056523287",
                "contactPersons": [
                    {
                        "phoneNumber": "+49 (591) 12345-60",
                        "vendor": "HPE",
                        "name": "Alice Marks4",
                        "type": "HARDWARE_CONTACT",
                        "mail": "alice4@hpe.com"
                    }
                ],
                "resellerId": "97292d03-7919-406c-a15b-39bf029e6d5a",
                "customerId": "5fb52fc3-86fd-4e1f-87cd-0f546fc8989a",
                "distributorId": "2d4c0f62-7e8f-4001-b16a-131db759c3f4"
            },
            "skuNumber": "HA151AC",
            "skuDescription": "HPE Hardware Maintenance Onsite Support",
            "supportPackage": "H7J34AC",
            "supportPackageDescription": "HPE Foundation Care 24x7 SVC",
            "startDate": null,
            "endDate": "1614470400000",
            "warrantyEndDate": null,
            "netPrice": "23.4",
            "discount": "-2.05",
            "listPrice": "48",
            "currencyCode": "EUR",
            "estimatedValueRenewal": "40"
        },
        {
            "document": {
                "id": "7e6b6976-cb1b-4b2a-9cf1-de9e768e8802",
                "type": "MultiNational Quote",
                "startDate": null,
                "endDate": "1677542400000",
                "currencyCode": "CUR",
                "languageCode": "fr",
                "totalNetPrice": "3,646.44",
                "vendorSpecificFields": {
                    "vendor": "HPE"
                },
                "documentNumber": "0056523288",
                "contactPersons": [
                    {
                        "phoneNumber": "+49 (591) 12345-61",
                        "vendor": "HPE",
                        "name": "Alice Marks5",
                        "type": "HARDWARE_CONTACT",
                        "mail": "alice5@hpe.com"
                    }
                ],
                "resellerId": "97292d03-7919-406c-a15b-39bf029e6d5a",
                "customerId": "5fb52fc3-86fd-4e1f-87cd-0f546fc8989a",
                "distributorId": "2d4c0f62-7e8f-4001-b16a-131db759c3f4"
            },
            "skuNumber": "HA151AC",
            "skuDescription": "HPE Hardware Maintenance Onsite Support",
            "supportPackage": "H7J34AC",
            "supportPackageDescription": "HPE Foundation Care 24x7 SVC",
            "startDate": null,
            "endDate": "1677542400000",
            "warrantyEndDate": null,
            "netPrice": "23.4",
            "discount": "-2.05",
            "listPrice": "48",
            "currencyCode": "EUR",
            "estimatedValueRenewal": "0"
        },
        {
            "document": {
                "id": "dbd3f08b-6bd1-4e28-8122-3004257879c0",
                "type": "MultiNational Quote",
                "startDate": null,
                "endDate": "1740700800000",
                "currencyCode": "CUR",
                "languageCode": "fr",
                "totalNetPrice": "6,376.15",
                "vendorSpecificFields": {
                    "vendor": "HPE"
                },
                "documentNumber": "0056490551",
                "contactPersons": [
                    {
                        "phoneNumber": "+49 (591) 12345-62",
                        "vendor": "HPE",
                        "name": "Alice Marks5",
                        "type": "HARDWARE_CONTACT",
                        "mail": "alice5@hpe.com"
                    }
                ],
                "resellerId": "97292d03-7919-406c-a15b-39bf029e6d5a",
                "customerId": "5fb52fc3-86fd-4e1f-87cd-0f546fc8989a",
                "distributorId": "2d4c0f62-7e8f-4001-b16a-131db759c3f4"
            },
            "skuNumber": "HA151AC",
            "skuDescription": "HPE Hardware Maintenance Onsite Support",
            "supportPackage": "H7J34AC",
            "supportPackageDescription": "HPE Foundation Care 24x7 SVC",
            "startDate": null,
            "endDate": "1740700800000",
            "warrantyEndDate": null,
            "netPrice": "23.4",
            "discount": "-2.05",
            "listPrice": "48",
            "currencyCode": "EUR",
            "estimatedValueRenewal": "24.3"
        },
        {
            "document": {
                "id": "688b9621-3244-464b-9468-3cd74f5eaacf",
                "type": "MultiNational Quote",
                "startDate": null,
                "endDate": "1614470400000",
                "currencyCode": "CUR",
                "languageCode": "fr",
                "totalNetPrice": "1,292.16",
                "vendorSpecificFields": {
                    "vendor": "HPE",
                    "said": "1234 4678 9012",
                    "groupId": "abc-de",
                    "groupDescription": "description"
                },
                "documentNumber": "0056523287",
                "contactPersons": [
                    {
                        "phoneNumber": "+49 (591) 12345-67",
                        "vendor": "HPE",
                        "name": "Alice Marks",
                        "type": "HARDWARE_CONTACT",
                        "mail": "alice1@hpe.com"
                    }
                ],
                "resellerId": "97292d03-7919-406c-a15b-39bf029e6d5a",
                "customerId": "5fb52fc3-86fd-4e1f-87cd-0f546fc8989a",
                "distributorId": "2d4c0f62-7e8f-4001-b16a-131db759c3f4"
            },
            "skuNumber": null,
            "skuDescription": null,
            "supportPackage": "H7J34AC",
            "supportPackageDescription": "HPE Foundation Care 24x7 SVC",
            "startDate": null,
            "endDate": "1614470400000",
            "warrantyEndDate": null,
            "netPrice": "23.4",
            "discount": "-2.05",
            "listPrice": "48",
            "currencyCode": "EUR",
            "estimatedValueRenewal": "145"
        }
    ]
}
